foo/__init__.py
foo/main.py
foo515114-0.5.0.dist-info/METADATA
foo515114-0.5.0.dist-info/WHEEL
foo515114-0.5.0.dist-info/top_level.txt
foo515114-0.5.0.dist-info/RECORD
